<?xml version="1.0" encoding="UTF-8"?>
<Database>
    <Kinds>
        <InsertOrIgnore Kind="KIND_UNLOCK"/>
    </Kinds>
    <RequirementSets>
        <Row RequirementSetId="REQSET_CIVILIZATION_GONDOR" RequirementSetType="REQUIREMENTSET_TEST_ALL"/>
    </RequirementSets>
    <Requirements>
        <Row RequirementId="REQ_CIVILIZATION_GONDOR" RequirementType="REQUIREMENT_PLAYER_CIVILIZATION_TYPE_MATCHES"/>
    </Requirements>
    <RequirementArguments>
        <Row RequirementId="REQ_CIVILIZATION_GONDOR" Name="CivilizationType" Value="CIVILIZATION_GONDOR"/>
    </RequirementArguments>
    <RequirementSetRequirements>
        <Row RequirementSetId="REQSET_CIVILIZATION_GONDOR" RequirementId="REQ_CIVILIZATION_GONDOR"/>
    </RequirementSetRequirements>
</Database>
<!-- generated with https://github.com/izica/civ7-modding-tools -->